{"is_source_file": false, "format": "CSS", "description": "This file contains CSS styles for the frontend of a point-of-sale system, defining styles for body layout and code elements.", "external_files": [], "external_methods": [], "published": [], "classes": [], "methods": [], "calls": [], "search-terms": ["CSS", "styles", "pos_frontend", "index.css", "body", "code", "font-family"], "state": 2, "file_id": 8, "knowledge_revision": 19, "git_revision": "87c321ada0259c67f3651edba2c9225089112483", "hash": "6c2104b8d219ed99234ae2d6329f4357", "format-version": 4, "code-base-name": "pos_frontend", "filename": "pos_frontend/src/index.css", "revision_history": [{"19": "87c321ada0259c67f3651edba2c9225089112483"}]}